README.rst
setup.cfg
setup.py
etnawrapper/__init__.py
etnawrapper/__main__.py
etnawrapper/constants.py
etnawrapper/errors.py
etnawrapper/etna.py
etnawrapper/watcher.py
etnawrapper.egg-info/PKG-INFO
etnawrapper.egg-info/SOURCES.txt
etnawrapper.egg-info/dependency_links.txt
etnawrapper.egg-info/entry_points.txt
etnawrapper.egg-info/requires.txt
etnawrapper.egg-info/top_level.txt