Metadata-Version: 1.1
Name: etnawrapper
Version: 2.3.3
Summary: API wrapper for ETNA' APIs
Home-page: https://github.com/tbobm/etnawrapper
Author: Theo 'Bob' Massard
Author-email: massar_t@etna-alternance.net
License: UNKNOWN
Download-URL: https://github.com/massard-t/etnawrapper/archive/2.3.3.tar.gz
Keywords: school,wrapper,APIs
Platform: UNKNOWN
Classifier: Development Status :: 5 - Production/Stable
Classifier: Intended Audience :: Developers
Classifier: Intended Audience :: System Administrators
Classifier: Operating System :: OS Independent
Classifier: Programming Language :: Python
